langchain_cloudsway/__init__.py
langchain_cloudsway/py.typed
langchain_cloudsway/smartsearch.py
langchain_cloudsway-0.1.3.dist-info/licenses/LICENSE
langchain_cloudsway-0.1.3.dist-info/METADATA
langchain_cloudsway-0.1.3.dist-info/WHEEL
langchain_cloudsway-0.1.3.dist-info/RECORD
